senza/__init__.py
senza/__main__.py
senza/arguments.py
senza/aws.py
senza/cli.py
senza/configuration.py
senza/definitions.py
senza/docker.py
senza/error_handling.py
senza/exceptions.py
senza/patch.py
senza/respawn.py
senza/stack_references.py
senza/traffic.py
senza/utils.py
senza/components/__init__.py
senza/components/auto_scaling_group.py
senza/components/configuration.py
senza/components/coreos_auto_configuration.py
senza/components/elastic_load_balancer.py
senza/components/elastic_load_balancer_v2.py
senza/components/elastigroup.py
senza/components/iam_role.py
senza/components/redis_cluster.py
senza/components/redis_node.py
senza/components/stups_auto_configuration.py
senza/components/subnet_auto_configuration.py
senza/components/taupage_auto_scaling_group.py
senza/components/weighted_dns_elastic_load_balancer.py
senza/components/weighted_dns_elastic_load_balancer_v2.py
senza/manaus/__init__.py
senza/manaus/acm.py
senza/manaus/boto_proxy.py
senza/manaus/cloudformation.py
senza/manaus/ec2.py
senza/manaus/elb.py
senza/manaus/exceptions.py
senza/manaus/iam.py
senza/manaus/route53.py
senza/manaus/utils.py
senza/spotinst/__init__.py
senza/spotinst/components/__init__.py
senza/spotinst/components/elastigroup_api.py
senza/stups/__init__.py
senza/stups/piu.py
senza/stups/taupage.py
senza/subcommands/__init__.py
senza/subcommands/config.py
senza/subcommands/root.py
senza/templates/__init__.py
senza/templates/_helper.py
senza/templates/bgapp.py
senza/templates/postgresapp.py
senza/templates/rediscluster.py
senza/templates/redisnode.py
senza/templates/webapp.py
stups_senza-2.1.143.dist-info/DESCRIPTION.rst
stups_senza-2.1.143.dist-info/METADATA
stups_senza-2.1.143.dist-info/RECORD
stups_senza-2.1.143.dist-info/WHEEL
stups_senza-2.1.143.dist-info/entry_points.txt
stups_senza-2.1.143.dist-info/metadata.json
stups_senza-2.1.143.dist-info/top_level.txt
