Metadata-Version: 2.0
Name: stups-senza
Version: 2.1.143
Summary: AWS Cloud Formation deployment CLI
Home-page: https://github.com/zalando-stups/senza
Author: Henning Jacobs
Author-email: henning.jacobs@zalando.de
License: Apache License 2.0
Keywords: aws cloud formation cf elb ec2 stups immutable stacks route53 boto
Platform: UNKNOWN
Classifier: Development Status :: 4 - Beta
Classifier: Environment :: Console
Classifier: Intended Audience :: Developers
Classifier: Intended Audience :: System Administrators
Classifier: License :: OSI Approved :: Apache Software License
Classifier: Operating System :: POSIX :: Linux
Classifier: Programming Language :: Python
Classifier: Programming Language :: Python :: 3.4
Classifier: Programming Language :: Python :: Implementation :: CPython
License-File: LICENSE
Requires-Dist: requests
Requires-Dist: arrow
Requires-Dist: clickclick (>=1.0)
Requires-Dist: pystache
Requires-Dist: PyYAML
Requires-Dist: dnspython (>=1.15.0)
Requires-Dist: stups-pierone (>=1.0.34)
Requires-Dist: boto3 (>=1.3.0)
Requires-Dist: botocore (>=1.4.10)
Requires-Dist: pytest (>=3.6.3)
Requires-Dist: raven
Requires-Dist: typing
